sciplt/__init__.py
sciplt/starter.py
sciplt-0.0.1.dist-info/METADATA
sciplt-0.0.1.dist-info/WHEEL
sciplt-0.0.1.dist-info/top_level.txt
sciplt-0.0.1.dist-info/RECORD
