Metadata-Version: 2.1
Name: sciplt
Version: 0.0.1
Summary: scientifc plot
Home-page: https://github.com/soonyenju/sciplt
Author: Dr. Songyan Zhu
Author-email: zhusy93@gmail.com
License: MIT Licence
Keywords: scientifc plot
Platform: any
